{"bones":[{"name":"root"},{"name":"main","parent":"root","length":161.48,"x":-0.11,"y":4.43,"rotation":89.09},{"name":"prev","parent":"root","length":102,"x":0.5,"y":608.3,"rotation":-89.54},{"name":"box","parent":"main","length":51.21,"x":14.91,"y":-0.41,"rotation":-0.45},{"name":"cristal","parent":"main","length":22.57,"x":178.99,"y":1.62,"rotation":0.9},{"name":"high","parent":"main","x":225.65,"y":2.35},{"name":"light","parent":"main","length":32.71,"x":206.3,"y":3.62,"rotation":-177.29},{"name":"low","parent":"main","x":124.52,"y":0.5},{"name":"stick","parent":"main","length":120.14,"x":333.18,"y":3.64,"rotation":0.9},{"name":"cristal_lightening","parent":"cristal","x":3.99,"y":0.28},{"name":"gear1","parent":"box","x":21.24,"y":3.25},{"name":"gear2","parent":"box","x":22.65,"y":38.69,"scaleX":0.627,"scaleY":0.627},{"name":"gear3","parent":"box","x":8.48,"y":50.45,"scaleX":0.429,"scaleY":0.429},{"name":"lightning","parent":"stick","x":83.14,"y":0.71}],"slots":[{"name":"light","bone":"light","attachment":"light"},{"name":"flash_light2","bone":"cristal_lightening","attachment":"flash_light"},{"name":"cristal","bone":"cristal","attachment":"cristal"},{"name":"flash_light","bone":"lightning","attachment":"flash_light"},{"name":"back","bone":"main","attachment":"back"},{"name":"tesla2_prev","bone":"prev","attachment":"tesla2_prev"},{"name":"stick_slot","bone":"stick","attachment":"1"},{"name":"high_slot","bone":"high","attachment":"h9"},{"name":"main","bone":"main","attachment":"glass"},{"name":"low_slot","bone":"low","attachment":"l1"},{"name":"box_back","bone":"box","attachment":"box_back"},{"name":"gear","bone":"gear1","attachment":"gear"},{"name":"gear2","bone":"gear2","attachment":"gear"},{"name":"gear22","bone":"gear3","attachment":"gear"},{"name":"box","bone":"box","attachment":"box_forw"}],"skins":{"default":{"back":{"back":{"x":79.13,"y":0.25,"rotation":-89.09,"width":186,"height":167}},"box":{"box_forw":{"x":21.53,"y":2.93,"rotation":-88.64,"width":174,"height":69}},"box_back":{"box_back":{"x":26.68,"y":0.62,"rotation":-88.64,"width":170,"height":53}},"cristal":{"cristal":{"x":4.15,"y":1.22,"rotation":-90,"width":22,"height":41}},"flash_light":{"flash_light":{"scaleX":1.212,"scaleY":1.127,"rotation":-90,"width":105,"height":105}},"flash_light2":{"flash_light":{"scaleX":1.212,"scaleY":1.127,"rotation":-90,"width":105,"height":105}},"gear":{"gear":{"x":0.58,"y":-0.34,"rotation":169.06,"width":38,"height":37}},"gear2":{"gear":{"x":0.58,"y":-0.34,"rotation":169.06,"width":38,"height":37}},"gear22":{"gear":{"x":0.58,"y":-0.34,"rotation":169.06,"width":38,"height":37}},"high_slot":{"h1":{"rotation":-89.09,"width":122,"height":24},"h2":{"rotation":-89.09,"width":122,"height":24},"h3":{"rotation":-89.09,"width":122,"height":24},"h4":{"rotation":-89.09,"width":122,"height":24},"h5":{"rotation":-89.09,"width":122,"height":24},"h6":{"rotation":-89.09,"width":122,"height":24},"h7":{"rotation":-89.09,"width":122,"height":24},"h8":{"rotation":-89.09,"width":122,"height":24},"h9":{"rotation":-89.09,"width":122,"height":24},"h10":{"rotation":-89.09,"width":122,"height":24},"h11":{"rotation":-89.09,"width":122,"height":24},"h12":{"rotation":-89.09,"width":122,"height":24}},"light":{"light":{"x":25.77,"y":-0.47,"rotation":88.19,"width":20,"height":57}},"low_slot":{"l1":{"rotation":-89.09,"width":123,"height":51},"l2":{"rotation":-89.09,"width":123,"height":51},"l3":{"rotation":-89.09,"width":123,"height":51},"l4":{"rotation":-89.09,"width":123,"height":51},"l5":{"rotation":-89.09,"width":123,"height":51},"l6":{"rotation":-89.09,"width":123,"height":51},"l8":{"rotation":-89.09,"width":123,"height":51},"l9":{"rotation":-89.09,"width":123,"height":51},"l10":{"rotation":-89.09,"width":123,"height":51}},"main":{"glass":{"x":181.73,"y":2.89,"rotation":-89.09,"width":118,"height":64}},"stick_slot":{"1":{"rotation":-90,"width":73,"height":244},"2":{"rotation":-90,"width":73,"height":244},"3":{"rotation":-90,"width":73,"height":244},"4":{"rotation":-90,"width":73,"height":244},"5":{"rotation":-90,"width":73,"height":243},"6":{"rotation":-90,"width":73,"height":243},"7":{"rotation":-90,"width":73,"height":243},"8":{"rotation":-90,"width":73,"height":243},"9":{"rotation":-90,"width":73,"height":243},"10":{"rotation":-90,"width":73,"height":243}},"tesla2_prev":{"tesla2_prev":{"x":404.63,"y":-3.18,"rotation":89.54,"width":186,"height":407}}}},"animations":{"attack":{"bones":{"main":{"rotate":[{"time":0,"angle":0,"curve":"stepped"},{"time":1.3333,"angle":0}],"translate":[{"time":0,"x":0,"y":0,"curve":"stepped"},{"time":1.3333,"x":0,"y":0}],"scale":[{"time":0,"x":1,"y":1,"curve":"stepped"},{"time":1.3333,"x":1,"y":1}]},"box":{"rotate":[{"time":0,"angle":0,"curve":"stepped"},{"time":1.3333,"angle":0}],"translate":[{"time":0,"x":0,"y":0},{"time":0.0883,"x":1.25,"y":-1.97},{"time":0.1767,"x":-0.02,"y":1.71},{"time":0.2651,"x":1.87,"y":-1.96},{"time":0.3535,"x":-0.02,"y":1.71},{"time":0.404,"x":0,"y":0},{"time":0.4608,"x":0.03,"y":-1.99},{"time":0.5176,"x":-0.02,"y":1.71},{"time":0.5744,"x":0.64,"y":-1.98},{"time":0.6313,"x":-0.02,"y":1.71},{"time":0.6818,"x":0,"y":0},{"time":0.7196,"x":-1.19,"y":-2.01},{"time":0.7575,"x":-0.02,"y":1.71},{"time":0.7954,"x":0.03,"y":-1.99},{"time":0.8333,"x":-0.02,"y":1.71},{"time":1.3333,"x":0,"y":0}],"scale":[{"time":0,"x":1,"y":1,"curve":"stepped"},{"time":1.3333,"x":1,"y":1}]},"high":{"rotate":[{"time":0,"angle":0,"curve":"stepped"},{"time":0.8333,"angle":0,"curve":"stepped"},{"time":1.3333,"angle":0}],"translate":[{"time":0,"x":0,"y":0,"curve":"stepped"},{"time":1.3333,"x":0,"y":0}],"scale":[{"time":0,"x":1,"y":1,"curve":"stepped"},{"time":0.8333,"x":1,"y":1,"curve":"stepped"},{"time":1.3333,"x":1,"y":1}]},"low":{"rotate":[{"time":0,"angle":0,"curve":"stepped"},{"time":1.3333,"angle":0}],"translate":[{"time":0,"x":0,"y":0,"curve":"stepped"},{"time":1.3333,"x":0,"y":0}],"scale":[{"time":0,"x":1,"y":1,"curve":"stepped"},{"time":1.3333,"x":1,"y":1}]},"stick":{"rotate":[{"time":0,"angle":0,"curve":"stepped"},{"time":1.3333,"angle":0}],"translate":[{"time":0,"x":0,"y":0,"curve":"stepped"},{"time":1.3333,"x":0,"y":0}],"scale":[{"time":0,"x":1,"y":1},{"time":0.8333,"x":1.019,"y":1.097},{"time":1.3333,"x":1,"y":1}]},"gear1":{"rotate":[{"time":0,"angle":0},{"time":0.0911,"angle":-84.7},{"time":0.1822,"angle":-178.3},{"time":0.2734,"angle":88.14},{"time":0.3645,"angle":0},{"time":0.4361,"angle":-84.7},{"time":0.5078,"angle":-178.3},{"time":0.5794,"angle":88.14},{"time":0.651,"angle":0},{"time":0.6966,"angle":-84.7},{"time":0.7421,"angle":-178.3},{"time":0.7877,"angle":88.14},{"time":0.8333,"angle":0},{"time":1.3333,"angle":148.98}],"translate":[{"time":0,"x":0,"y":0,"curve":"stepped"},{"time":1.3333,"x":0,"y":0}],"scale":[{"time":0,"x":1,"y":1,"curve":"stepped"},{"time":1.3333,"x":1,"y":1}]},"gear3":{"rotate":[{"time":0,"angle":0},{"time":0.0946,"angle":88.65},{"time":0.1893,"angle":179.19},{"time":0.284,"angle":-91.12},{"time":0.3787,"angle":0},{"time":0.445,"angle":88.65},{"time":0.5113,"angle":179.19},{"time":0.5776,"angle":-91.12},{"time":0.6439,"angle":0},{"time":0.6912,"angle":88.65},{"time":0.7386,"angle":179.19},{"time":0.7859,"angle":-91.12},{"time":0.8333,"angle":76.77},{"time":1.3333,"angle":0}],"translate":[{"time":0,"x":0,"y":0,"curve":"stepped"},{"time":1.3333,"x":0,"y":0}],"scale":[{"time":0,"x":0.999,"y":0.999,"curve":"stepped"},{"time":1.3333,"x":0.999,"y":0.999}]},"gear2":{"rotate":[{"time":0,"angle":0},{"time":0.0911,"angle":-84.7},{"time":0.1822,"angle":-178.3},{"time":0.2734,"angle":88.14},{"time":0.3645,"angle":0},{"time":0.4361,"angle":-84.7},{"time":0.5078,"angle":-178.3},{"time":0.5794,"angle":88.14},{"time":0.651,"angle":0},{"time":0.6966,"angle":-84.7},{"time":0.7421,"angle":-178.3},{"time":0.7877,"angle":88.14},{"time":0.8333,"angle":-110.17},{"time":1.3333,"angle":0}],"translate":[{"time":0,"x":0,"y":0,"curve":"stepped"},{"time":1.3333,"x":0,"y":0}],"scale":[{"time":0,"x":1,"y":1,"curve":"stepped"},{"time":1.3333,"x":1,"y":1}]},"lightning":{"rotate":[{"time":0,"angle":0,"curve":"stepped"},{"time":1.3333,"angle":0}],"translate":[{"time":0,"x":0,"y":0,"curve":"stepped"},{"time":1.3333,"x":0,"y":0}],"scale":[{"time":0,"x":0.121,"y":0.112,"curve":"stepped"},{"time":0.7,"x":0.121,"y":0.112,"curve":[0.25,0,0.678,0.26]},{"time":0.8333,"x":2.369,"y":2.031,"curve":[0.281,0.92,0.75,1]},{"time":0.9666,"x":0.121,"y":0.112,"curve":"stepped"},{"time":1.3333,"x":0.121,"y":0.112}]},"cristal":{"rotate":[{"time":0,"angle":0,"curve":"stepped"},{"time":0.8333,"angle":0,"curve":"stepped"},{"time":1.3333,"angle":0}],"translate":[{"time":0,"x":-9.21,"y":-0.14,"curve":[0.421,0.02,0.581,0.99]},{"time":0.0333,"x":0,"y":0,"curve":[0.427,0,0.535,1]},{"time":0.0538,"x":-1.23,"y":-2.23},{"time":0.0949,"x":3.53,"y":4.05},{"time":0.1361,"x":5.17,"y":-1.05},{"time":0.1772,"x":-0.51,"y":3.72},{"time":0.2183,"x":-1.23,"y":-2.23},{"time":0.2594,"x":3.53,"y":4.05},{"time":0.3005,"x":5.17,"y":-1.05},{"time":0.3416,"x":-0.51,"y":3.72},{"time":0.3827,"x":-1.23,"y":-2.23},{"time":0.4238,"x":3.53,"y":4.05},{"time":0.4649,"x":5.17,"y":-1.05},{"time":0.506,"x":-0.51,"y":3.72},{"time":0.5424,"x":-1.23,"y":-2.23},{"time":0.5666,"x":3.53,"y":4.05},{"time":0.5909,"x":5.17,"y":-1.05},{"time":0.6151,"x":-0.51,"y":3.72},{"time":0.6515,"x":-1.23,"y":-2.23},{"time":0.6757,"x":3.53,"y":4.05},{"time":0.7,"x":5.17,"y":-1.05},{"time":0.7242,"x":-0.51,"y":3.72},{"time":0.7606,"x":-1.23,"y":-2.23},{"time":0.7848,"x":3.53,"y":4.05},{"time":0.809,"x":5.17,"y":-1.05},{"time":0.8333,"x":-0.51,"y":3.72},{"time":0.9,"x":0,"y":0,"curve":[0.427,0,0.535,1]},{"time":1.3333,"x":-9.21,"y":-0.14}],"scale":[{"time":0,"x":1,"y":1},{"time":0.8333,"x":1.366,"y":1.366},{"time":0.9,"x":1,"y":1,"curve":"stepped"},{"time":1.3333,"x":1,"y":1}]},"light":{"rotate":[{"time":0,"angle":0,"curve":"stepped"},{"time":1.3333,"angle":0}],"translate":[{"time":0,"x":0,"y":0,"curve":"stepped"},{"time":1.3333,"x":0,"y":0}],"scale":[{"time":0,"x":1,"y":1},{"time":0.8333,"x":1,"y":2.344,"curve":[0.055,0.96,0.75,1]},{"time":1.3333,"x":1,"y":1}]},"cristal_lightening":{"rotate":[{"time":0,"angle":0,"curve":"stepped"},{"time":1.3333,"angle":0}],"translate":[{"time":0,"x":0,"y":0,"curve":"stepped"},{"time":1.3333,"x":0,"y":0}],"scale":[{"time":0,"x":0.1,"y":0.1,"curve":"stepped"},{"time":0.7,"x":0.1,"y":0.1,"curve":[0.25,0,0.767,0.14]},{"time":0.8333,"x":0.737,"y":0.737,"curve":[0.215,0.92,0.75,1]},{"time":0.9666,"x":0.1,"y":0.1,"curve":"stepped"},{"time":1.3333,"x":0.1,"y":0.1}]}},"slots":{"high_slot":{"attachment":[{"time":0,"name":"h1"},{"time":0.032,"name":"h2"},{"time":0.0641,"name":"h3"},{"time":0.0961,"name":"h4"},{"time":0.1282,"name":"h5"},{"time":0.1602,"name":"h6"},{"time":0.1923,"name":"h7"},{"time":0.2243,"name":"h8"},{"time":0.2564,"name":"h9"},{"time":0.2884,"name":"h10"},{"time":0.3205,"name":"h11"},{"time":0.3525,"name":"h12"},{"time":0.3846,"name":"h1"},{"time":0.4079,"name":"h2"},{"time":0.4312,"name":"h3"},{"time":0.4545,"name":"h4"},{"time":0.4778,"name":"h5"},{"time":0.5011,"name":"h6"},{"time":0.5244,"name":"h7"},{"time":0.5477,"name":"h8"},{"time":0.571,"name":"h9"},{"time":0.5944,"name":"h10"},{"time":0.6177,"name":"h11"},{"time":0.641,"name":"h1"},{"time":0.6585,"name":"h2"},{"time":0.6759,"name":"h3"},{"time":0.6934,"name":"h4"},{"time":0.7109,"name":"h5"},{"time":0.7284,"name":"h6"},{"time":0.7459,"name":"h7"},{"time":0.7634,"name":"h8"},{"time":0.7808,"name":"h9"},{"time":0.7983,"name":"h10"},{"time":0.8158,"name":"h11"},{"time":0.8333,"name":"h12"},{"time":0.8666,"name":"h1"},{"time":0.904,"name":"h2"},{"time":0.9414,"name":"h3"},{"time":0.9788,"name":"h4"},{"time":1.0162,"name":"h5"},{"time":1.0536,"name":"h6"},{"time":1.091,"name":"h7"},{"time":1.1284,"name":"h8"},{"time":1.1658,"name":"h9"},{"time":1.2032,"name":"h10"},{"time":1.2405,"name":"h11"},{"time":1.3,"name":"h12"},{"time":1.3333,"name":"h1"}]},"low_slot":{"attachment":[{"time":0,"name":"l10"},{"time":0.0435,"name":"l9"},{"time":0.087,"name":"l8"},{"time":0.1306,"name":"l6"},{"time":0.1741,"name":"l5"},{"time":0.2176,"name":"l4"},{"time":0.2612,"name":"l3"},{"time":0.3047,"name":"l2"},{"time":0.3483,"name":"l1"},{"time":0.3918,"name":"l10"},{"time":0.4217,"name":"l9"},{"time":0.4517,"name":"l8"},{"time":0.4816,"name":"l6"},{"time":0.5115,"name":"l5"},{"time":0.5415,"name":"l4"},{"time":0.5714,"name":"l3"},{"time":0.6013,"name":"l2"},{"time":0.6313,"name":"l1"},{"time":0.6657,"name":"l10"},{"time":0.6866,"name":"l9"},{"time":0.7076,"name":"l8"},{"time":0.7285,"name":"l6"},{"time":0.7495,"name":"l5"},{"time":0.7704,"name":"l4"},{"time":0.7914,"name":"l3"},{"time":0.8123,"name":"l2"},{"time":0.8333,"name":"l1"},{"time":0.8574,"name":"l10"},{"time":0.9127,"name":"l9"},{"time":0.9681,"name":"l8"},{"time":1.0234,"name":"l6"},{"time":1.0787,"name":"l5"},{"time":1.134,"name":"l4"},{"time":1.1893,"name":"l3"},{"time":1.2446,"name":"l2"},{"time":1.3,"name":"l1"},{"time":1.3333,"name":"l10"}]},"stick_slot":{"attachment":[{"time":0,"name":"1"},{"time":0.0933,"name":"2"},{"time":0.1666,"name":"3"},{"time":0.2666,"name":"4"},{"time":0.3333,"name":"5"},{"time":0.4,"name":"6"},{"time":0.4666,"name":"7"},{"time":0.5333,"name":"8"},{"time":0.6,"name":"9"},{"time":0.6333,"name":"10"},{"time":0.8333,"name":"10"},{"time":0.8666,"name":"9"},{"time":0.9,"name":"8"},{"time":0.9333,"name":"7"},{"time":0.9666,"name":"6"},{"time":1,"name":"5"},{"time":1.0333,"name":"4"},{"time":1.0666,"name":"3"},{"time":1.1,"name":"2"},{"time":1.1333,"name":"1"},{"time":1.3333,"name":"1"}]}}},"main":{"bones":{"main":{"rotate":[{"time":0,"angle":0,"curve":"stepped"},{"time":3.3333,"angle":0}],"translate":[{"time":0,"x":0,"y":0,"curve":"stepped"},{"time":3.3333,"x":0,"y":0}],"scale":[{"time":0,"x":1,"y":1,"curve":"stepped"},{"time":3.3333,"x":1,"y":1}]},"box":{"rotate":[{"time":0,"angle":0,"curve":"stepped"},{"time":3.3333,"angle":0}],"translate":[{"time":0,"x":0,"y":0,"curve":"stepped"},{"time":3.3333,"x":0,"y":0}],"scale":[{"time":0,"x":1,"y":1,"curve":"stepped"},{"time":3.3333,"x":1,"y":1}]},"high":{"rotate":[{"time":0,"angle":0,"curve":"stepped"},{"time":3.3333,"angle":0}],"translate":[{"time":0,"x":0,"y":0,"curve":"stepped"},{"time":3.3333,"x":0,"y":0}],"scale":[{"time":0,"x":1,"y":1,"curve":"stepped"},{"time":3.3333,"x":1,"y":1}]},"low":{"rotate":[{"time":0,"angle":0,"curve":"stepped"},{"time":3.3333,"angle":0}],"translate":[{"time":0,"x":0,"y":0,"curve":"stepped"},{"time":3.3333,"x":0,"y":0}],"scale":[{"time":0,"x":1,"y":1,"curve":"stepped"},{"time":3.3333,"x":1,"y":1}]},"stick":{"rotate":[{"time":0,"angle":0,"curve":"stepped"},{"time":3.3333,"angle":0}],"translate":[{"time":0,"x":0,"y":0,"curve":[0.443,0.06,0.647,0.27]},{"time":1.6666,"x":-3.14,"y":-0.05,"curve":[0.253,0.59,0.54,0.97]},{"time":3.3333,"x":0,"y":0}],"scale":[{"time":0,"x":1,"y":1,"curve":"stepped"},{"time":3.3333,"x":1,"y":1}]},"gear1":{"rotate":[{"time":0,"angle":0,"curve":"stepped"},{"time":3.3333,"angle":0}],"translate":[{"time":0,"x":0,"y":0,"curve":"stepped"},{"time":3.3333,"x":0,"y":0}],"scale":[{"time":0,"x":1,"y":1,"curve":"stepped"},{"time":3.3333,"x":1,"y":1}]},"gear3":{"rotate":[{"time":0,"angle":0,"curve":"stepped"},{"time":3.3333,"angle":0}],"translate":[{"time":0,"x":0,"y":0,"curve":"stepped"},{"time":3.3333,"x":0,"y":0}],"scale":[{"time":0,"x":0.999,"y":0.999,"curve":"stepped"},{"time":3.3333,"x":0.999,"y":0.999}]},"gear2":{"rotate":[{"time":0,"angle":0,"curve":"stepped"},{"time":3.3333,"angle":0}],"translate":[{"time":0,"x":0,"y":0,"curve":"stepped"},{"time":3.3333,"x":0,"y":0}],"scale":[{"time":0,"x":1,"y":1,"curve":"stepped"},{"time":3.3333,"x":1,"y":1}]},"lightning":{"rotate":[{"time":0,"angle":0,"curve":"stepped"},{"time":3.3333,"angle":0}],"translate":[{"time":0,"x":0,"y":0,"curve":"stepped"},{"time":3.3333,"x":0,"y":0}],"scale":[{"time":0,"x":0.121,"y":0.112,"curve":"stepped"},{"time":3.3333,"x":0.121,"y":0.112}]},"cristal_lightening":{"rotate":[{"time":0,"angle":0,"curve":"stepped"},{"time":3.3333,"angle":0}],"translate":[{"time":0,"x":0,"y":0,"curve":"stepped"},{"time":3.3333,"x":0,"y":0}],"scale":[{"time":0,"x":0.1,"y":0.1,"curve":"stepped"},{"time":3.3333,"x":0.1,"y":0.1}]},"light":{"rotate":[{"time":0,"angle":0,"curve":"stepped"},{"time":3.3333,"angle":0}],"translate":[{"time":0,"x":0,"y":0,"curve":"stepped"},{"time":3.3333,"x":0,"y":0}],"scale":[{"time":0,"x":1,"y":1,"curve":"stepped"},{"time":3.3333,"x":1,"y":1}]},"cristal":{"rotate":[{"time":0,"angle":0,"curve":"stepped"},{"time":3.3333,"angle":0}],"translate":[{"time":0,"x":-9.21,"y":-0.14,"curve":[0.443,0.06,0.647,0.27]},{"time":1.6666,"x":-1.51,"y":-0.02,"curve":[0.253,0.59,0.54,0.97]},{"time":3.3333,"x":-9.21,"y":-0.14}],"scale":[{"time":0,"x":1,"y":1,"curve":"stepped"},{"time":3.3333,"x":1,"y":1}]}},"slots":{"high_slot":{"attachment":[{"time":0,"name":"h1"},{"time":0.4,"name":"h1"},{"time":0.4333,"name":"h2"},{"time":0.4666,"name":"h3"},{"time":0.5,"name":"h4"},{"time":0.5333,"name":"h5"},{"time":0.5666,"name":"h6"},{"time":0.6,"name":"h7"},{"time":0.6333,"name":"h8"},{"time":0.6666,"name":"h9"},{"time":0.7,"name":"h10"},{"time":0.7333,"name":"h11"},{"time":0.7666,"name":"h12"},{"time":2.6666,"name":"h12"},{"time":2.7,"name":"h11"},{"time":2.7333,"name":"h10"},{"time":2.7666,"name":"h9"},{"time":2.8,"name":"h8"},{"time":2.8333,"name":"h7"},{"time":2.8666,"name":"h6"},{"time":2.9,"name":"h5"},{"time":2.9333,"name":"h4"},{"time":2.9666,"name":"h3"},{"time":3,"name":"h2"},{"time":3.0333,"name":"h1"},{"time":3.3333,"name":"h1"}]},"low_slot":{"attachment":[{"time":0,"name":"l10"},{"time":0.0666,"name":"l9"},{"time":0.1333,"name":"l8"},{"time":0.2,"name":"l6"},{"time":0.2666,"name":"l5"},{"time":0.3333,"name":"l4"},{"time":0.4,"name":"l3"},{"time":0.4666,"name":"l2"},{"time":0.5333,"name":"l1"},{"time":1.4666,"name":"l1"},{"time":1.5333,"name":"l2"},{"time":1.6,"name":"l3"},{"time":1.6666,"name":"l4"},{"time":1.7333,"name":"l5"},{"time":1.8,"name":"l6"},{"time":1.8666,"name":"l8"},{"time":1.9333,"name":"l9"},{"time":2,"name":"l10"},{"time":3.3333,"name":"l10"}]},"stick_slot":{"attachment":[{"time":0,"name":"1"},{"time":3.3333,"name":"1"}]}}}}}